festim/__init__.py
festim/_version.py
festim/generic_simulation.py
festim/h_transport_problem.py
festim/helpers.py
festim/initial_condition.py
festim/nonlinear_problem.py
festim/settings.py
festim/stepsize.py
festim/boundary_conditions/__init__.py
festim/boundary_conditions/boundary_condition.py
festim/boundary_conditions/dirichlets/__init__.py
festim/boundary_conditions/dirichlets/custom_dc.py
festim/boundary_conditions/dirichlets/dc_imp.py
festim/boundary_conditions/dirichlets/dirichlet_bc.py
festim/boundary_conditions/dirichlets/henrys_bc.py
festim/boundary_conditions/dirichlets/sieverts_bc.py
festim/boundary_conditions/fluxes/__init__.py
festim/boundary_conditions/fluxes/convective_flux.py
festim/boundary_conditions/fluxes/dissociation_flux.py
festim/boundary_conditions/fluxes/flux_bc.py
festim/boundary_conditions/fluxes/flux_custom.py
festim/boundary_conditions/fluxes/mass_flux.py
festim/boundary_conditions/fluxes/recombination_flux.py
festim/boundary_conditions/fluxes/surface_kinetics.py
festim/concentration/__init__.py
festim/concentration/concentration.py
festim/concentration/mobile.py
festim/concentration/theta.py
festim/concentration/traps/__init__.py
festim/concentration/traps/extrinsic_trap.py
festim/concentration/traps/neutron_induced_trap.py
festim/concentration/traps/trap.py
festim/concentration/traps/traps.py
festim/exports/__init__.py
festim/exports/export.py
festim/exports/exports.py
festim/exports/trap_density_xdmf.py
festim/exports/txt_export.py
festim/exports/xdmf_export.py
festim/exports/derived_quantities/__init__.py
festim/exports/derived_quantities/adsorbed_hydrogen.py
festim/exports/derived_quantities/average_surface.py
festim/exports/derived_quantities/average_volume.py
festim/exports/derived_quantities/derived_quantities.py
festim/exports/derived_quantities/derived_quantity.py
festim/exports/derived_quantities/hydrogen_flux.py
festim/exports/derived_quantities/maximum_surface.py
festim/exports/derived_quantities/maximum_volume.py
festim-1.4.1.post1.dist-info/licenses/LICENSE
festim-1.4.1.post1.dist-info/METADATA
festim-1.4.1.post1.dist-info/WHEEL
festim-1.4.1.post1.dist-info/top_level.txt
festim-1.4.1.post1.dist-info/RECORD
