Metadata-Version: 2.4
Name: festim
Version: 1.4.1.post1
Summary: Finite element simulations of hydrogen transport
Author-email: Remi Delaporte-Mathurin <rdelaportemathurin@gmail.com>
License:                                  Apache License
Project-URL: Repository, https://github.com/festim-dev/FESTIM
Project-URL: Issues, https://github.com/festim-dev/FESTIM/issues
Classifier: Natural Language :: English
Classifier: Topic :: Scientific/Engineering
Classifier: Programming Language :: Python :: 3.10
Classifier: Programming Language :: Python :: 3.11
Classifier: Programming Language :: Python :: 3.12
Classifier: License :: OSI Approved :: Apache Software License
Classifier: Operating System :: OS Independent
Requires-Python: >=3.10
License-File: LICENSE
Provides-Extra: tests
Requires-Dist: pytest>=5.4.3; extra == "tests"
Requires-Dist: ipyparallel; extra == "tests"
Dynamic: license-file
